<annotation><filename>color-190519-143900870.jpg</filename><folder>users/pasteldew//objects</folder><source><submittedBy>HeeJun Song</submittedBy></source><imagesize><nrows>455</nrows><ncols>455</ncols></imagesize><object><name>desk</name><deleted>0</deleted><verified>0</verified><occluded>no</occluded><attributes/><parts><hasparts/><ispartof/></parts><date>20-May-2019 06:22:34</date><id>0</id><segm><username>anonymous</username><box><xmin>315</xmin><ymin>291</ymin><xmax>454</xmax><ymax>454</ymax></box><mask>color-190519-143900870_mask_0.png</mask><scribbles><xmin>273</xmin><ymin>232.75</ymin><xmax>455</xmax><ymax>455</ymax><scribble_name>color-190519-143900870_scribble_0.png</scribble_name></scribbles></segm></object><object><name>desk</name><deleted>0</deleted><verified>0</verified><occluded>no</occluded><attributes/><parts><hasparts/><ispartof/></parts><date>20-May-2019 06:24:40</date><id>1</id><segm><username>anonymous</username><box><xmin>358</xmin><ymin>166</ymin><xmax>454</xmax><ymax>210</ymax></box><mask>color-190519-143900870_mask_1.png</mask><scribbles><xmin>335.5</xmin><ymin>155</ymin><xmax>455</xmax><ymax>227</ymax><scribble_name>color-190519-143900870_scribble_1.png</scribble_name></scribbles></segm></object><object><name>desk</name><deleted>0</deleted><verified>0</verified><occluded>no</occluded><attributes/><parts><hasparts/><ispartof/></parts><date>20-May-2019 06:32:01</date><id>2</id><segm><username>pasteldew</username><box><xmin>105</xmin><ymin>232</ymin><xmax>454</xmax><ymax>430</ymax></box><mask>color-190519-143900870_mask_2.png</mask><scribbles><xmin>8.75</xmin><ymin>182.75</ymin><xmax>455</xmax><ymax>455</ymax><scribble_name>color-190519-143900870_scribble_2.png</scribble_name></scribbles></segm></object><object><name>book</name><deleted>0</deleted><verified>0</verified><occluded>no</occluded><attributes/><parts><hasparts/><ispartof/></parts><date>20-May-2019 06:32:13</date><id>3</id><segm><username>pasteldew</username><box><xmin>143</xmin><ymin>234</ymin><xmax>210</xmax><ymax>250</ymax></box><mask>color-190519-143900870_mask_3.png</mask><scribbles><xmin>117.75</xmin><ymin>229.75</ymin><xmax>233.25</xmax><ymax>261.25</ymax><scribble_name>color-190519-143900870_scribble_3.png</scribble_name></scribbles></segm></object><object><name>books</name><deleted>0</deleted><verified>0</verified><occluded>no</occluded><attributes/><parts><hasparts/><ispartof/></parts><date>20-May-2019 06:32:33</date><id>4</id><segm><username>pasteldew</username><box><xmin>205</xmin><ymin>234</ymin><xmax>273</xmax><ymax>266</ymax></box><mask>color-190519-143900870_mask_4.png</mask><scribbles><xmin>176.5</xmin><ymin>227.5</ymin><xmax>305.5</xmax><ymax>278.5</ymax><scribble_name>color-190519-143900870_scribble_4.png</scribble_name></scribbles></segm></object><object><name>books</name><deleted>0</deleted><verified>0</verified><occluded>no</occluded><attributes/><parts><hasparts/><ispartof/></parts><date>20-May-2019 06:32:44</date><id>5</id><segm><username>pasteldew</username><box><xmin>252</xmin><ymin>216</ymin><xmax>321</xmax><ymax>238</ymax></box><mask>color-190519-143900870_mask_5.png</mask><scribbles><xmin>234.75</xmin><ymin>210.25</ymin><xmax>350.25</xmax><ymax>250.75</ymax><scribble_name>color-190519-143900870_scribble_5.png</scribble_name></scribbles></segm></object><object><name>books</name><deleted>0</deleted><verified>0</verified><occluded>no</occluded><attributes/><parts><hasparts/><ispartof/></parts><date>20-May-2019 06:32:57</date><id>6</id><segm><username>pasteldew</username><box><xmin>418</xmin><ymin>199</ymin><xmax>454</xmax><ymax>231</ymax></box><mask>color-190519-143900870_mask_6.png</mask><scribbles><xmin>395</xmin><ymin>192.25</ymin><xmax>455</xmax><ymax>250.75</ymax><scribble_name>color-190519-143900870_scribble_6.png</scribble_name></scribbles></segm></object><object><name>box</name><deleted>0</deleted><verified>0</verified><occluded>no</occluded><attributes/><parts><hasparts/><ispartof/></parts><date>20-May-2019 06:33:05</date><id>7</id><segm><username>pasteldew</username><box><xmin>40</xmin><ymin>197</ymin><xmax>100</xmax><ymax>219</ymax></box><mask>color-190519-143900870_mask_7.png</mask><scribbles><xmin>31.5</xmin><ymin>194.75</ymin><xmax>100.5</xmax><ymax>220.25</ymax><scribble_name>color-190519-143900870_scribble_7.png</scribble_name></scribbles></segm></object><object><name>book</name><deleted>0</deleted><verified>0</verified><occluded>no</occluded><attributes/><parts><hasparts/><ispartof/></parts><date>20-May-2019 06:33:17</date><id>8</id><segm><username>pasteldew</username><box><xmin>92</xmin><ymin>197</ymin><xmax>134</xmax><ymax>214</ymax></box><mask>color-190519-143900870_mask_8.png</mask><scribbles><xmin>69.75</xmin><ymin>195</ymin><xmax>143.25</xmax><ymax>225</ymax><scribble_name>color-190519-143900870_scribble_8.png</scribble_name></scribbles></segm></object><object><name>laptop</name><deleted>0</deleted><verified>0</verified><occluded>no</occluded><attributes/><parts><hasparts/><ispartof/></parts><date>20-May-2019 06:33:33</date><id>9</id><segm><username>pasteldew</username><box><xmin>185</xmin><ymin>140</ymin><xmax>250</xmax><ymax>192</ymax></box><mask>color-190519-143900870_mask_9.png</mask><scribbles><xmin>153.5</xmin><ymin>124.25</ymin><xmax>276.5</xmax><ymax>212.75</ymax><scribble_name>color-190519-143900870_scribble_9.png</scribble_name></scribbles></segm></object><object><name>desk</name><deleted>0</deleted><verified>0</verified><occluded>no</occluded><attributes/><parts><hasparts/><ispartof/></parts><date>20-May-2019 06:34:10</date><id>10</id><segm><username>pasteldew</username><box><xmin>4</xmin><ymin>194</ymin><xmax>303</xmax><ymax>330</ymax></box><mask>color-190519-143900870_mask_10.png</mask><scribbles><xmin>0</xmin><ymin>145.75</ymin><xmax>367.5</xmax><ymax>363.25</ymax><scribble_name>color-190519-143900870_scribble_10.png</scribble_name></scribbles></segm></object><object><name>chair</name><deleted>0</deleted><verified>0</verified><occluded>no</occluded><attributes/><parts><hasparts/><ispartof/></parts><date>20-May-2019 06:34:16</date><id>11</id><segm><username>pasteldew</username><box><xmin>101</xmin><ymin>180</ymin><xmax>131</xmax><ymax>193</ymax></box><mask>color-190519-143900870_mask_11.png</mask><scribbles><xmin>98.25</xmin><ymin>178.5</ymin><xmax>132.75</xmax><ymax>193.5</ymax><scribble_name>color-190519-143900870_scribble_11.png</scribble_name></scribbles></segm></object><object><name>plastic_bottle</name><deleted>0</deleted><verified>0</verified><occluded>no</occluded><attributes></attributes><parts><hasparts></hasparts><ispartof></ispartof></parts><date>20-May-2019 06:46:08</date><id>12</id><segm><username>pasteldew</username><box><xmin>4</xmin><ymin>364</ymin><xmax>27</xmax><ymax>421</ymax></box><mask>color-190519-143900870_mask_12.png</mask><scribbles><xmin>4</xmin><ymin>356.5</ymin><xmax>28</xmax><ymax>425.5</ymax><scribble_name>color-190519-143900870_scribble_12.png</scribble_name></scribbles></segm></object><object><name>plastic_bottle</name><deleted>0</deleted><verified>0</verified><occluded>no</occluded><attributes></attributes><parts><hasparts></hasparts><ispartof></ispartof></parts><date>20-May-2019 06:46:24</date><id>13</id><segm><username>pasteldew</username><box><xmin>36</xmin><ymin>301</ymin><xmax>81</xmax><ymax>434</ymax></box><mask>color-190519-143900870_mask_13.png</mask><scribbles><xmin>21.5</xmin><ymin>272.75</ymin><xmax>90.5</xmax><ymax>455</ymax><scribble_name>color-190519-143900870_scribble_13.png</scribble_name></scribbles></segm></object></annotation>